{
  "schema_version": 1,
  "repo": {
    "name": "srcpkg",
    "path": "/home/hartley/projects/personal/ticket-sys/test-repos/srcpkg",
    "branch": "main",
    "head": "2a0ae0f",
    "total_commits": 2,
    "generated_at": "2026-06-13 21:25 UTC"
  },
  "package_roots": {
    "": "src"
  },
  "stats": {
    "file_count": 4,
    "total_loc": 15,
    "contributor_count": 1,
    "edge_count": 2
  },
  "languages": [
    {
      "name": "Python",
      "files": 3,
      "loc": 15
    },
    {
      "name": "Config",
      "files": 1,
      "loc": 0
    }
  ],
  "files": [
    {
      "path": "pyproject.toml",
      "lang": "Config",
      "loc": 0,
      "size": 138,
      "commits": 1,
      "last_commit": "2026-06-13"
    },
    {
      "path": "src/mypkg/__init__.py",
      "lang": "Python",
      "loc": 5,
      "size": 92,
      "commits": 1,
      "last_commit": "2026-06-13"
    },
    {
      "path": "src/mypkg/core.py",
      "lang": "Python",
      "loc": 5,
      "size": 78,
      "commits": 1,
      "last_commit": "2026-06-13"
    },
    {
      "path": "tests/test_core.py",
      "lang": "Python",
      "loc": 5,
      "size": 92,
      "commits": 1,
      "last_commit": "2026-06-13"
    }
  ],
  "edges": [
    {
      "source": "src/mypkg/__init__.py",
      "target": "src/mypkg/core.py"
    },
    {
      "source": "tests/test_core.py",
      "target": "src/mypkg/core.py"
    }
  ]
}